arithmetic_lib/__init__.py
arithmetic_lib/arithmetic.py
arithmeticop-2.0.dist-info/METADATA
arithmeticop-2.0.dist-info/WHEEL
arithmeticop-2.0.dist-info/top_level.txt
arithmeticop-2.0.dist-info/RECORD
