Metadata-Version: 2.1
Name: arithmeticop
Version: 2.0
Summary: A simple arithmetic operations library
Author: Suraj Kumar
Author-email: Surajksharma2304@gmail.com
